{
  "timestamp" : "2025-02-03T12:35:19Z",
  "count_outdated" : 4603,
  "uniques_outdated" : 2351,
  "count" : 4632,
  "uniques" : 2375,
  "clones" : [
    {
      "timestamp": "2025-01-21T00:00:00Z",
      "count": 1,
      "count_minmax": [ 1, 1 ],
      "count_decinc": [ 0, 1 ],
      "uniques": 1,
      "uniques_minmax": [ 1, 1 ],
      "uniques_decinc": [ 0, 1 ]
    },
    {
      "timestamp": "2025-01-27T00:00:00Z",
      "count": 1,
      "count_minmax": [ 1, 1 ],
      "count_decinc": [ 0, 1 ],
      "uniques": 1,
      "uniques_minmax": [ 1, 1 ],
      "uniques_decinc": [ 0, 1 ]
    },
    {
      "timestamp": "2025-01-30T00:00:00Z",
      "count": 2,
      "count_minmax": [ 2, 2 ],
      "count_decinc": [ 0, 2 ],
      "uniques": 2,
      "uniques_minmax": [ 2, 2 ],
      "uniques_decinc": [ 0, 2 ]
    },
    {
      "timestamp": "2025-01-31T00:00:00Z",
      "count": 2,
      "count_minmax": [ 1, 2 ],
      "count_decinc": [ 0, 2 ],
      "uniques": 2,
      "uniques_minmax": [ 1, 2 ],
      "uniques_decinc": [ 0, 2 ]
    },
    {
      "timestamp": "2025-02-01T00:00:00Z",
      "count": 2,
      "count_minmax": [ 1, 2 ],
      "count_decinc": [ 0, 2 ],
      "uniques": 1,
      "uniques_minmax": [ 1, 1 ],
      "uniques_decinc": [ 0, 1 ]
    },
    {
      "timestamp": "2025-02-02T00:00:00Z",
      "count": 8,
      "count_minmax": [ 1, 8 ],
      "count_decinc": [ 0, 8 ],
      "uniques": 6,
      "uniques_minmax": [ 1, 6 ],
      "uniques_decinc": [ 0, 6 ]
    },
    {
      "timestamp": "2025-02-03T00:00:00Z",
      "count": 13,
      "count_minmax": [ 13, 13 ],
      "count_decinc": [ 0, 13 ],
      "uniques": 11,
      "uniques_minmax": [ 11, 11 ],
      "uniques_decinc": [ 0, 11 ]
    }
  ]
}
