{
  "timestamp" : "2025-11-27T01:03:13Z",
  "count_outdated" : 3142,
  "uniques_outdated" : 1085,
  "count" : 3172,
  "uniques" : 1098,
  "views" : [
    {
      "timestamp": "2025-11-13T00:00:00Z",
      "count": 2,
      "count_minmax": [ 1, 2 ],
      "count_decinc": [ 0, 2 ],
      "uniques": 2,
      "uniques_minmax": [ 1, 2 ],
      "uniques_decinc": [ 0, 2 ]
    },
    {
      "timestamp": "2025-11-14T00:00:00Z",
      "count": 1,
      "count_minmax": [ 1, 1 ],
      "count_decinc": [ 0, 1 ],
      "uniques": 1,
      "uniques_minmax": [ 1, 1 ],
      "uniques_decinc": [ 0, 1 ]
    },
    {
      "timestamp": "2025-11-15T00:00:00Z",
      "count": 1,
      "count_minmax": [ 1, 1 ],
      "count_decinc": [ 0, 1 ],
      "uniques": 1,
      "uniques_minmax": [ 1, 1 ],
      "uniques_decinc": [ 0, 1 ]
    },
    {
      "timestamp": "2025-11-16T00:00:00Z",
      "count": 14,
      "count_minmax": [ 14, 14 ],
      "count_decinc": [ 0, 14 ],
      "uniques": 2,
      "uniques_minmax": [ 2, 2 ],
      "uniques_decinc": [ 0, 2 ]
    },
    {
      "timestamp": "2025-11-17T00:00:00Z",
      "count": 1,
      "count_minmax": [ 1, 1 ],
      "count_decinc": [ 0, 1 ],
      "uniques": 1,
      "uniques_minmax": [ 1, 1 ],
      "uniques_decinc": [ 0, 1 ]
    },
    {
      "timestamp": "2025-11-18T00:00:00Z",
      "count": 7,
      "count_minmax": [ 6, 7 ],
      "count_decinc": [ 0, 7 ],
      "uniques": 2,
      "uniques_minmax": [ 1, 2 ],
      "uniques_decinc": [ 0, 2 ]
    },
    {
      "timestamp": "2025-11-20T00:00:00Z",
      "count": 1,
      "count_minmax": [ 1, 1 ],
      "count_decinc": [ 0, 1 ],
      "uniques": 1,
      "uniques_minmax": [ 1, 1 ],
      "uniques_decinc": [ 0, 1 ]
    },
    {
      "timestamp": "2025-11-22T00:00:00Z",
      "count": 1,
      "count_minmax": [ 1, 1 ],
      "count_decinc": [ 0, 1 ],
      "uniques": 1,
      "uniques_minmax": [ 1, 1 ],
      "uniques_decinc": [ 0, 1 ]
    },
    {
      "timestamp": "2025-11-23T00:00:00Z",
      "count": 1,
      "count_minmax": [ 1, 1 ],
      "count_decinc": [ 0, 1 ],
      "uniques": 1,
      "uniques_minmax": [ 1, 1 ],
      "uniques_decinc": [ 0, 1 ]
    },
    {
      "timestamp": "2025-11-26T00:00:00Z",
      "count": 1,
      "count_minmax": [ 1, 1 ],
      "count_decinc": [ 0, 1 ],
      "uniques": 1,
      "uniques_minmax": [ 1, 1 ],
      "uniques_decinc": [ 0, 1 ]
    }
  ]
}
